<?xml version='1.1' encoding='UTF-8'?>
<fingerprint>
  <timestamp>2018-04-26 21:12:45.251 UTC</timestamp>
  <original>
    <name>TestMaven/org.jenkins-ci.main:jenkins-test-harness</name>
    <number>6</number>
  </original>
  <md5sum>a4442839d37e7843514a88efe61b70b8</md5sum>
  <fileName>org.jenkins-ci.main:jenkins-test-harness:pom.xml</fileName>
  <usages>
    <entry>
      <string>TestMaven</string>
      <ranges>6</ranges>
    </entry>
    <entry>
      <string>TestMaven/org.jenkins-ci.main:jenkins-test-harness</string>
      <ranges>6</ranges>
    </entry>
  </usages>
  <facets/>
</fingerprint>